LICENSE
MANIFEST.in
README.md
setup.py
signalrcore/__init__.py
signalrcore/helpers.py
signalrcore/hub_connection_builder.py
signalrcore/subject.py
signalrcorePPI.egg-info/PKG-INFO
signalrcorePPI.egg-info/SOURCES.txt
signalrcorePPI.egg-info/dependency_links.txt
signalrcorePPI.egg-info/requires.txt
signalrcorePPI.egg-info/top_level.txt
signalrcore/hub/__init__.py
signalrcore/hub/auth_hub_connection.py
signalrcore/hub/base_hub_connection.py
signalrcore/hub/errors.py
signalrcore/hub/handlers.py
signalrcore/messages/__init__.py
signalrcore/messages/base_message.py
signalrcore/messages/cancel_invocation_message.py
signalrcore/messages/close_message.py
signalrcore/messages/completion_message.py
signalrcore/messages/invocation_message.py
signalrcore/messages/message_type.py
signalrcore/messages/ping_message.py
signalrcore/messages/stream_invocation_message.py
signalrcore/messages/stream_item_message.py
signalrcore/messages/handshake/__init__.py
signalrcore/messages/handshake/request.py
signalrcore/messages/handshake/response.py
signalrcore/protocol/__init__.py
signalrcore/protocol/base_hub_protocol.py
signalrcore/protocol/json_hub_protocol.py
signalrcore/protocol/messagepack_protocol.py
signalrcore/protocol/handshake/__init__.py
signalrcore/transport/__init__.py
signalrcore/transport/base_transport.py
signalrcore/transport/websockets/__init__.py
signalrcore/transport/websockets/connection.py
signalrcore/transport/websockets/reconnection.py
signalrcore/transport/websockets/websocket_transport.py
test/__init__.py
test/base_test_case.py
test/client_streaming_test.py
test/configuration_test.py
test/open_close_test.py
test/reconnection_test.py
test/send_auth_errors_test.py
test/send_auth_test.py
test/send_test.py
test/streaming_test.py