Metadata-Version: 2.1
Name: signalrcorePPI
Version: 0.9.2
Summary: A Python SignalR Core client(json and messagepack), with invocation auth and two way streaming. Compatible with azure / serverless functions. Also with automatic reconnect and manually reconnect.
Home-page: https://github.com/SistemasPPI/signalrcorePPI
Author: mandrewcito
Author-email: anbaalo@gmail.com
License: UNKNOWN
Keywords: signalr core client 3.1
Platform: UNKNOWN
Classifier: Programming Language :: Python :: 3.6
License-File: LICENSE
